{
  "entries": [
    {
      "id": 1,
      "date": "2021-12-24",
      "concept": "Array Method*****",
      "entry": "We learned about arrays.",
      "mood": "happy"
    },
    {
      "concept": "test",
      "date": "2021-10-27",
      "entry": "test",
      "mood": "tired",
      "id": 2
    },
    {
      "concept": "tes",
      "date": "2021-10-27",
      "entry": "test",
      "mood": "sad",
      "id": 3
    },
    {
      "concept": "APi",
      "date": "2021-10-27",
      "entry": "Finished Journal API Saving",
      "mood": "tired",
      "id": 4
    },
    {
      "concept": "",
      "date": "",
      "entry": "",
      "mood": "Open this select menu",
      "id": 5
    },
    {
      "concept": "APIIII",
      "date": "2021-10-27",
      "entry": "APIII",
      "mood": "happy",
      "id": 6
    },
    {
      "concept": "Learned how to edit",
      "date": "2021-11-11",
      "entry": "Today we finished learning CRUD by learning how to edit. ",
      "mood": "happy",
      "id": 7
    }
  ]
}